pybrams/__init__.py
pybrams/brams/__init__.py
pybrams/brams/adsb.py
pybrams/brams/file.py
pybrams/brams/location.py
pybrams/brams/system.py
pybrams/brams/fetch/__init__.py
pybrams/brams/fetch/api.py
pybrams/brams/fetch/archive.py
pybrams/brams/fetch/downloader.py
pybrams/brams/formats/__init__.py
pybrams/brams/formats/wav.py
pybrams/brams/formats/zip.py
pybrams/config/config.json
pybrams/data/pybrams/event/meteor/snr_rise_time_db_fine_10000_5512.json
pybrams/data/pybrams/event/meteor/snr_rise_time_db_fine_10000_6048.json
pybrams/data/pybrams/optical/cams/SummaryMeteorLog_Cams.txt
pybrams/event/__init__.py
pybrams/event/meteor.py
pybrams/optical/__init__.py
pybrams/optical/cams.py
pybrams/optical/constants.py
pybrams/processing/__init__.py
pybrams/processing/airplane_removal.py
pybrams/processing/beacon_removal.py
pybrams/processing/calibrator_removal.py
pybrams/processing/constants.py
pybrams/processing/interference_removal.py
pybrams/processing/pps.py
pybrams/processing/series.py
pybrams/processing/signal.py
pybrams/scripts/__init__.py
pybrams/scripts/availability.py
pybrams/scripts/cache.py
pybrams/scripts/cams.py
pybrams/scripts/config.py
pybrams/scripts/get.py
pybrams/scripts/location.py
pybrams/scripts/prepare_meteors.py
pybrams/scripts/psd.py
pybrams/scripts/pybrams.py
pybrams/scripts/spectrogram.py
pybrams/scripts/system.py
pybrams/scripts/trajectory.py
pybrams/scripts/wavinfo.py
pybrams/trajectory/__init__.py
pybrams/trajectory/analyzer.py
pybrams/trajectory/constants.py
pybrams/trajectory/mcmc.py
pybrams/trajectory/scam.py
pybrams/trajectory/solve_setup.py
pybrams/trajectory/solver.py
pybrams/utils/__init__.py
pybrams/utils/cache.py
pybrams/utils/config.py
pybrams/utils/constants.py
pybrams/utils/coordinates.py
pybrams/utils/data.py
pybrams/utils/geometry.py
pybrams/utils/http.py
pybrams/utils/interval.py
pybrams/utils/kinematic.py
pybrams/utils/plot.py
pybrams-0.1.4.dist-info/licenses/LICENSE.txt
pybrams-0.1.4.dist-info/METADATA
pybrams-0.1.4.dist-info/WHEEL
pybrams-0.1.4.dist-info/entry_points.txt
pybrams-0.1.4.dist-info/top_level.txt
pybrams-0.1.4.dist-info/RECORD
