Metadata-Version: 2.4
Name: pybrams
Version: 0.1.4
Summary: BRAMS project Python package
Author-email: Antoine Calegaro <antoine.calegaro@aeronomie.be>, Joachim Balis <joachim.balis@aeronomie.be>
License-Expression: MIT
Project-URL: homepage, https://brams.aeronomie.be
Project-URL: repository, https://gitlab.aeronomie.be/ae/brams/pybrams
Project-URL: documentation, https://gitlab.aeronomie.be/ae/brams/pybrams
Keywords: brams,meteor
Classifier: Programming Language :: Python :: 3
Requires-Python: >=3.10
License-File: LICENSE.txt
Requires-Dist: numpy
Requires-Dist: autograd
Requires-Dist: KDEpy
Requires-Dist: matplotlib
Requires-Dist: pykml
Requires-Dist: requests
Requires-Dist: scipy
Requires-Dist: scikit-image
Requires-Dist: dill
Requires-Dist: tqdm
Requires-Dist: rich
Dynamic: license-file
